synodic-0.1.1.dev3.dist-info/METADATA
synodic-0.1.1.dev3.dist-info/WHEEL
synodic/__init__.py
synodic-0.1.1.dev3.dist-info/RECORD
